BeginnersbookCYuyanJiaochengChuyi/README.md
BeginnersbookCYuyanJiaochengChuyi/__init__.py
BeginnersbookCYuyanJiaochengChuyi/__main__.py
BeginnersbookCYuyanJiaochengChuyi/file.epub
BeginnersbookCYuyanJiaochengChuyi/index.html
BeginnersbookCYuyanJiaochengChuyi/css/__init__.py
BeginnersbookCYuyanJiaochengChuyi/css/annotations.css
BeginnersbookCYuyanJiaochengChuyi/css/main.css
BeginnersbookCYuyanJiaochengChuyi/css/normalize.css
BeginnersbookCYuyanJiaochengChuyi/css/popup.css
BeginnersbookCYuyanJiaochengChuyi/font/__init__.py
BeginnersbookCYuyanJiaochengChuyi/font/fontello.eot
BeginnersbookCYuyanJiaochengChuyi/font/fontello.svg
BeginnersbookCYuyanJiaochengChuyi/font/fontello.ttf
BeginnersbookCYuyanJiaochengChuyi/font/fontello.woff
BeginnersbookCYuyanJiaochengChuyi/img/__init__.py
BeginnersbookCYuyanJiaochengChuyi/img/annotator-glyph-sprite.png
BeginnersbookCYuyanJiaochengChuyi/img/annotator-icon-sprite.png
BeginnersbookCYuyanJiaochengChuyi/img/apple-touch-icon.png
BeginnersbookCYuyanJiaochengChuyi/img/cancelfullscreen.png
BeginnersbookCYuyanJiaochengChuyi/img/close.png
BeginnersbookCYuyanJiaochengChuyi/img/fullscreen.png
BeginnersbookCYuyanJiaochengChuyi/img/loader.gif
BeginnersbookCYuyanJiaochengChuyi/img/menu-icon.png
BeginnersbookCYuyanJiaochengChuyi/img/save.png
BeginnersbookCYuyanJiaochengChuyi/img/saved.png
BeginnersbookCYuyanJiaochengChuyi/img/settings-s.png
BeginnersbookCYuyanJiaochengChuyi/img/settings.png
BeginnersbookCYuyanJiaochengChuyi/img/star.png
BeginnersbookCYuyanJiaochengChuyi/js/__init__.py
BeginnersbookCYuyanJiaochengChuyi/js/epub.js
BeginnersbookCYuyanJiaochengChuyi/js/epub.min.js
BeginnersbookCYuyanJiaochengChuyi/js/epub.min.map
BeginnersbookCYuyanJiaochengChuyi/js/hooks.min.js
BeginnersbookCYuyanJiaochengChuyi/js/hooks.min.map
BeginnersbookCYuyanJiaochengChuyi/js/reader.js
BeginnersbookCYuyanJiaochengChuyi/js/reader.js.map
BeginnersbookCYuyanJiaochengChuyi/js/reader.min.js
BeginnersbookCYuyanJiaochengChuyi/js/reader.min.map
beginnersbook_c_yuyan_jiaocheng_chuyi-2024.3.4.0.dist-info/METADATA
beginnersbook_c_yuyan_jiaocheng_chuyi-2024.3.4.0.dist-info/WHEEL
beginnersbook_c_yuyan_jiaocheng_chuyi-2024.3.4.0.dist-info/entry_points.txt
beginnersbook_c_yuyan_jiaocheng_chuyi-2024.3.4.0.dist-info/top_level.txt
beginnersbook_c_yuyan_jiaocheng_chuyi-2024.3.4.0.dist-info/RECORD
